{"GlobalPropertiesHash":"/i2pdqQL1BofFOg+p4QlTdMrMyHCABLm60MYuknDt3M=","FingerprintPatternsHash":"gq3WsqcKBUGTSNle7RKKyXRIwh7M8ccEqOqYvIzoM04=","PropertyOverridesHash":"8ZRc1sGeVrPBx4lD717BgRaQekyh78QKV9SKsdt638U=","InputHashes":["hLIADMtTn/m8/iZVSWRsLbW8HbJ\u002BDRDn4vfRJUg4Ors=","gDlW6eU4P96h4vK3QY1MqK69tfNynhxQ7qG8szHSB2U=","a14WLzPYgik8HVBnmh2\u002BIyrTRQ2NVS8AYncjUPsz6pk=","N6BezkyOpIqCD\u002BCiVyxh6ucmjHy\u002BuEiN7lcSpJIWq70="],"CachedAssets":{"hLIADMtTn/m8/iZVSWRsLbW8HbJ\u002BDRDn4vfRJUg4Ors=":{"Identity":"C:\\Users\\4093094\\source\\repos\\Arista_ZebraTablet\\Arista_ZebraTablet\\Arista_ZebraTablet\\wwwroot\\app.css","SourceId":"Arista_ZebraTablet","SourceType":"Discovered","ContentRoot":"C:\\Users\\4093094\\source\\repos\\Arista_ZebraTablet\\Arista_ZebraTablet\\Arista_ZebraTablet\\wwwroot\\","BasePath":"/","RelativePath":"app#[.{fingerprint}]?.css","AssetKind":"All","AssetMode":"All","AssetRole":"Primary","AssetMergeBehavior":null,"AssetMergeSource":"","RelatedAsset":null,"AssetTraitName":null,"AssetTraitValue":null,"Fingerprint":"obgb1x923p","Integrity":"nAPExVxs4MSkXKnxvGIYwMYuD37zfvuOz6q6ILLNXLU=","CopyToOutputDirectory":"Never","CopyToPublishDirectory":"PreserveNewest","OriginalItemSpec":"wwwroot\\app.css","FileLength":416,"LastWriteTime":"2025-10-09T06:45:29.8103134+00:00"},"gDlW6eU4P96h4vK3QY1MqK69tfNynhxQ7qG8szHSB2U=":{"Identity":"C:\\Users\\4093094\\source\\repos\\Arista_ZebraTablet\\Arista_ZebraTablet\\Arista_ZebraTablet\\wwwroot\\index.html","SourceId":"Arista_ZebraTablet","SourceType":"Discovered","ContentRoot":"C:\\Users\\4093094\\source\\repos\\Arista_ZebraTablet\\Arista_ZebraTablet\\Arista_ZebraTablet\\wwwroot\\","BasePath":"/","RelativePath":"index#[.{fingerprint}]?.html","AssetKind":"All","AssetMode":"All","AssetRole":"Primary","AssetMergeBehavior":null,"AssetMergeSource":"","RelatedAsset":null,"AssetTraitName":null,"AssetTraitValue":null,"Fingerprint":"5uwdphbt5x","Integrity":"fXR7nHy/Ob0EiAw1Hd0oU3fvXs8x4OEuzeUOQJ7uIfg=","CopyToOutputDirectory":"Never","CopyToPublishDirectory":"PreserveNewest","OriginalItemSpec":"wwwroot\\index.html","FileLength":806,"LastWriteTime":"2025-10-09T06:45:29.8153189+00:00"}},"CachedCopyCandidates":{}}